pySprida/__init__.py
pySprida/__main__.py
pySprida/_version.py
pySprida/mainWindow.py
pySprida/data/__init__.py
pySprida/data/consolePrinter.py
pySprida/data/dataContainer.py
pySprida/data/group.py
pySprida/data/groupType.py
pySprida/data/lpData.py
pySprida/data/solution.py
pySprida/data/subject.py
pySprida/data/subjectType.py
pySprida/data/teacher.py
pySprida/gui/__init__.py
pySprida/gui/lpSolverWindow.py
pySprida/gui/lpsolveredit.py
pySprida/gui/main.py
pySprida/gui/solution_window.py
pySprida/solver/__init__.py
pySprida/solver/lpSolver.py
pySprida/solver/solver.py
tests/__init__.py
pySprida-0.0.4.dist-info/LICENSE
pySprida-0.0.4.dist-info/METADATA
pySprida-0.0.4.dist-info/WHEEL
pySprida-0.0.4.dist-info/top_level.txt
pySprida-0.0.4.dist-info/RECORD
