Metadata-Version: 2.1
Name: pySprida
Version: 0.0.4
Summary: UNKNOWN
Home-page: UNKNOWN
Author: Paul Kruse
Maintainer: Paul Kruse
Maintainer-email: paul.kruse@posteo.de
License: MIT
Platform: UNKNOWN
Requires-Python: >=3.7
Requires-Dist: texttable
Requires-Dist: mip
Requires-Dist: pandas
Requires-Dist: pyqt5
Requires-Dist: numpy
Requires-Dist: xlsxwriter
